coredotcloud/__init__.py
coredotcloud/cli.py
coredotcloud/collector.py
coredotcloud/config.py
coredotcloud/main.py
coredotcloud/sender.py
coredotcloud/util.py
coredotcloud/version.py
tests/__init__.py
tests/test_coredotcloud.py
tests/test_elasticsearch.py
tests/test_util.py
coredotcloud-0.7.6.dist-info/AUTHORS.rst
coredotcloud-0.7.6.dist-info/LICENSE
coredotcloud-0.7.6.dist-info/METADATA
coredotcloud-0.7.6.dist-info/WHEEL
coredotcloud-0.7.6.dist-info/entry_points.txt
coredotcloud-0.7.6.dist-info/top_level.txt
coredotcloud-0.7.6.dist-info/RECORD
