Metadata-Version: 2.2
Name: coredotcloud
Version: 0.7.6
Summary: A simple system monitoring tool for CoreDotCloud
Home-page: https://github.com/coredottoday/coredotcloud
Author: CoreDotToday
Author-email: dev@core.today
Classifier: Programming Language :: Python :: 3
Classifier: License :: OSI Approved :: MIT License
Classifier: Operating System :: OS Independent
Requires-Python: >=3.7
License-File: LICENSE
License-File: AUTHORS.rst
Requires-Dist: psutil
Requires-Dist: requests
Requires-Dist: gputil
Dynamic: author
Dynamic: author-email
Dynamic: classifier
Dynamic: description
Dynamic: description-content-type
Dynamic: home-page
Dynamic: requires-dist
Dynamic: requires-python
Dynamic: summary
